fbchat_muqit/__init__.py
fbchat_muqit/client.py
fbchat_muqit/graphql.py
fbchat_muqit/muqit.py
fbchat_muqit/realtime.py
fbchat_muqit/state.py
fbchat_muqit/topics.json
fbchat_muqit/topicsbackup.json
fbchat_muqit/events/dispatcher.py
fbchat_muqit/exception/errors.py
fbchat_muqit/facebook/client.py
fbchat_muqit/facebook/response_parser.py
fbchat_muqit/logging/logger.py
fbchat_muqit/messenger/client.py
fbchat_muqit/models/__init__.py
fbchat_muqit/models/attachment.py
fbchat_muqit/models/message.py
fbchat_muqit/models/messagesData.py
fbchat_muqit/models/notifications.py
fbchat_muqit/models/presence.py
fbchat_muqit/models/themes.py
fbchat_muqit/models/thread.py
fbchat_muqit/models/thread_actions.py
fbchat_muqit/models/timestamps.py
fbchat_muqit/models/typing.py
fbchat_muqit/models/user.py
fbchat_muqit/models/deltas/__init__.py
fbchat_muqit/models/deltas/attachments_deltas.py
fbchat_muqit/models/deltas/custom_type.py
fbchat_muqit/models/deltas/delta_wrapper.py
fbchat_muqit/models/deltas/group_deltas.py
fbchat_muqit/models/deltas/parse_thread_messages.py
fbchat_muqit/models/deltas/parser.py
fbchat_muqit/models/deltas/payloads.py
fbchat_muqit/models/mqtt_response/create_group_thread.py
fbchat_muqit/models/mqtt_response/response.py
fbchat_muqit/models/mqtt_response/search_message.py
fbchat_muqit/models/mqtt_response/send_message.py
fbchat_muqit/utils/graphqlHelper.py
fbchat_muqit/utils/stateHelper.py
fbchat_muqit/utils/utils.py
fbchat_muqit-1.2.1.dist-info/METADATA
fbchat_muqit-1.2.1.dist-info/WHEEL
fbchat_muqit-1.2.1.dist-info/licenses/LICENSE-BSD.md
fbchat_muqit-1.2.1.dist-info/licenses/LICENSE.md
fbchat_muqit-1.2.1.dist-info/RECORD
