Metadata-Version: 2.4
Name: fbchat-muqit
Version: 1.2.1
Summary: A powerful Facebook Messenger API to interact with Facebook and Messenger.
Author-email: Muhammad MuQiT <togashiyuuta1111@gmail.com>
License: GPL-3.0-or-later
License-File: LICENSE-BSD.md
License-File: LICENSE.md
Keywords: api,asyncio,chat,facebook,fbchat,fbchat-muqit,fca,messenger
Classifier: Framework :: AsyncIO
Classifier: Intended Audience :: Developers
Classifier: License :: OSI Approved :: GNU General Public License v3 (GPLv3)
Classifier: Programming Language :: Python :: 3
Classifier: Programming Language :: Python :: 3.10
Classifier: Programming Language :: Python :: 3.11
Classifier: Programming Language :: Python :: 3.12
Classifier: Topic :: Software Development :: Libraries :: Python Modules
Requires-Python: >=3.10
Requires-Dist: aenum>=3.1.15
Requires-Dist: aiofiles>=25.1.0
Requires-Dist: aiohttp-socks>=0.10.2
Requires-Dist: aiohttp>=3.11.11
Requires-Dist: aiomqtt>=2.3.0
Requires-Dist: brotli>=1.2.0
Requires-Dist: filetype>=1.2.0
Requires-Dist: msgspec>=0.19.0
Requires-Dist: puremagic>=1.30
Requires-Dist: yarl>=1.18.3
